pmg_maze/__init__.py
pmg_maze/pmg.py
PMG_Maze-1.0.0a0.dist-info/METADATA
PMG_Maze-1.0.0a0.dist-info/WHEEL
PMG_Maze-1.0.0a0.dist-info/top_level.txt
PMG_Maze-1.0.0a0.dist-info/RECORD
