Metadata-Version: 2.1
Name: PMG-Maze
Version: 1.0.0a0
Summary: A library for maze generation
Requires-Dist: numpy
Requires-Dist: Pillow
Requires-Dist: tqdm
